Workbook

Sheet Task Tracker
A1: IT Department — Cross-Team Task Tracker 2026
A2: Request ID | B2: Task ID | C2: Task Name | D2: Team | E2: Category | F2: Dept Tag | G2: Priority | H2: Status | I2: Phase | J2: Assignee | K2: Team Lead | L2: Created Date | M2: Deadline | N2: Completed Date | O2: Dependencies | P2: Notes
A3: 2400155 | C3: [CR] [2400155] [MKT] Develop Mission Tracking Page for Promotion | D3: Dev Team B | E3: CR | F3: MKT | G3: Medium | I3: Q2 | K3: minhvo@phs.vn | M3: minhvo2565 | N3: minhvo2565 | O3: 2400155
A4: 2084592 | C4: [CR] [2084592] [RMD] Calculate interest for accounts using special interest rate products | D4: Dev Team B | E4: CR | F4: RMD | G4: Medium | I4: Q2 | K4: minhvo@phs.vn | M4: minhvo2565 | N4: minhvo2565 | O4: 2084592
A5: 2275303 | C5: [CR] [2275303] [SS] Enhance securities depository features via the PHS Elite Trading application | D5: Dev Team B | E5: CR | F5: SS | G5: Medium | I5: Q2 | K5: minhvo@phs.vn | M5: minhvo2565 | N5: minhvo2565 | O5: 2275303
A6: 2275303 | C6: [CR] [2275303] [SS] Enhance securities depository features via the PHS Elite Trading application | D6: Team Mobile | E6: CR | F6: SS | G6: Medium | I6: Q2 | K6: phongvo@phs.vn | N6: phongvo2440 | O6: 2275303
A7: 2084592 | C7: [CR] [2084592] [RMD] Declare Limit & Type For Account Using Special Product on FLEX system | D7: Team Mobile | E7: CR | F7: RMD | G7: Medium | I7: Q2 | K7: phongvo@phs.vn | M7: phongvo2440 | N7: phongvo2440 | O7: 2084592
A8: 2149046 | C8: [CR] [2149046] [IT] EKYC | D8: Team Mobile | E8: CR | F8: IT | G8: Medium | I8: Q2 | K8: phongvo@phs.vn | N8: phongvo2440 | O8: 2149046
A9: 2283752 | C9: [CR] [2283752] [SS] Send Notification via Elite App and mail all right issue | D9: Team Mobile | E9: CR | F9: SS | G9: Medium | I9: Q2 | K9: phongvo@phs.vn | N9: phongvo2440 | O9: 2283752
A10: 2238356 | C10: [CR] [2238356] [MSD] ADVANCE MARGIN FOR DERIVATIVES | D10: Team Mobile | E10: CR | F10: MSD | G10: Medium | I10: Q2 | K10: phongvo@phs.vn | M10: phongvo2440 | N10: phongvo2440 | O10: 2238356
A11: 2335404 | C11: [CR] [2335404] Upgrade the automatic limit adjustment feature | D11: Team Mobile | E11: CR | G11: Medium | I11: Q2 | K11: phongvo@phs.vn | M11: phongvo2440 | N11: phongvo2440 | O11: 2335404
A12: 2400155 | C12: [CR] [2400155] Marketing - Develop Mission Tracking Page for Promotion Q1.2026 | D12: Team Mobile | E12: CR | G12: Medium | I12: Q2 | K12: phongvo@phs.vn | M12: phongvo2440 | N12: phongvo2440 | O12: 2400155
A13: 2310394 | C13: [CR] [2310394] Tax analysis and estimation tools for investors (Phase 1) | D13: Team Mobile | E13: CR | G13: Medium | I13: Q2 | K13: phongvo@phs.vn | M13: phongvo2440 | N13: phongvo2440
A14: 2335404 | C14: [CR] [2335404] [RMD] Upgrade the automatic limit adjustment feature on Customer Portal Admin | D14: Dev Team B | E14: CR | F14: RMD | G14: Medium | I14: Q2 | K14: minhvo@phs.vn | M14: minhvo2565 | N14: minhvo2565 | O14: 2335404
A15: 2400155 | C15: [CR] [2400155] [MKT] Develop Mission Tracking Page for Promotion | D15: Dev Team B | E15: CR | F15: MKT | G15: Medium | I15: Q2 | K15: minhvo@phs.vn | M15: minhvo2565 | N15: minhvo2565 | O15: 2400155
A16: 2403987 | C16: [CR] [2403987] [SS] Loyalty System - Phase 1 | D16: Dev Team B | E16: CR | F16: SS | G16: Medium | I16: Q2 | K16: minhvo@phs.vn | M16: minhvo2565 | N16: minhvo2565
A17: 2129248 | C17: [CR] [2129248] [RMD] Add Special room information for Locations | D17: Dev Team B | E17: CR | F17: RMD | G17: Medium | I17: Q2 | K17: minhvo@phs.vn | M17: minhvo2565 | N17: minhvo2565
A18: 2084592 | C18: [CR] [2084592] [RMD] Calculate interest for accounts using special interest rate products | D18: Dev Team B | E18: CR | F18: RMD | G18: Medium | I18: Q2 | K18: minhvo@phs.vn | M18: minhvo2565 | N18: minhvo2565 | O18: 2084592
A19: 2275303 | C19: [CR] [2275303] [SS] Enhance securities depository features via the PHS Elite Trading application | D19: Dev Team B | E19: CR | F19: SS | G19: Medium | I19: Q2 | K19: minhvo@phs.vn | M19: minhvo2565 | N19: minhvo2565 | O19: 2275303
A20: 2423945 | C20: [CR] [2423945] [SS] Enhance the promotional declaration feature on the Admin Portal | D20: Dev Team B | E20: CR | F20: SS | G20: Medium | I20: Q2 | K20: minhvo@phs.vn | M20: minhvo2565 | N20: minhvo2565
A21: 2154685 | C21: [CR] [2154685] [BMD] Upgrade fund certificate trading feature on Mobile app | D21: Dev Team B | E21: CR | F21: BMD | G21: Medium | I21: Q2 | K21: minhvo@phs.vn | M21: minhvo2565 | N21: minhvo2565 | O21: 2154685
A22: 2385402 | C22: [CR] [2385402] [MKT] Create popup on web phs.vn to promote for landing page PHS 20 Years Anniversary | D22: Dev Team B | E22: CR | F22: MKT | G22: Medium | I22: Q2 | K22: minhvo@phs.vn | M22: minhvo2565 | N22: minhvo2565
A23: 2197982 | C23: [CR] [2197982] [RS] Research Landing Page: All Features & Phase 1 Execution | D23: Dev Team B | E23: CR | F23: RS | G23: Medium | I23: Q2 | K23: minhvo@phs.vn | M23: minhvo2565 | N23: minhvo2565
A24: 1954732 | C24: [CR] [1954732] [HR] HR report automation | D24: Dev Team B | E24: CR | F24: HR | G24: Medium | I24: Backlog | K24: minhvo@phs.vn | M24: minhvo2565 | N24: minhvo2565
A25: 2426812 | C25: [CR] [2426812] [MKT] Merge CCC & RS chatbot into one Master Client Chatbot | D25: Dev Team B | E25: CR | F25: MKT | G25: Medium | I25: Backlog | K25: minhvo@phs.vn | M25: minhvo2565 | N25: minhvo2565
A26: 2415056 | C26: [CR] [2415056] [MKT] Implementation of “Partner Offers” on PHS Mobile App | D26: Dev Team B | E26: CR | F26: MKT | G26: Medium | I26: Backlog | K26: minhvo@phs.vn | M26: minhvo2565 | N26: minhvo2565 | O26: 2415056
A27: 2330515 | C27: [CR] [2330515] [RMD] IPO Share Subscription Feature | D27: Dev Team B | E27: CR | F27: RMD | G27: Medium | I27: Backlog | K27: minhvo@phs.vn | M27: minhvo2565 | N27: minhvo2565 | O27: 2330515
A28: 2425861 | C28: [CR] [2425861] [RS] Research Portal: Phase 2 | D28: Dev Team B | E28: CR | F28: RS | G28: Medium | I28: Backlog | K28: minhvo@phs.vn | M28: minhvo2565 | N28: minhvo2565
A29: 1923581 | C29: [CR] [1923581] [RMD] Tool to control the number of positions that need to be closed out | D29: Dev Team B | E29: CR | F29: RMD | G29: Medium | I29: Backlog | K29: minhvo@phs.vn | M29: minhvo2565 | N29: minhvo2565
A30: 2329940 | C30: [CR] [2329940] [RS] AI Chatbot Integration for Elite Mobile App & Xpro Web Trading | D30: Team Mobile | E30: CR | F30: RS | G30: Low | I30: Q2 | K30: phongvo@phs.vn | N30: phongvo2440
A31: 2306127 | C31: [CR] [2306127] INB_ Proposal to implement the mobile app notifications for Elite Seeds | D31: Team Mobile | E31: CR | G31: Medium | I31: Q2 | K31: phongvo@phs.vn | M31: phongvo2440 | N31: phongvo2440
A32: 2372910 | C32: [CR][2372910] [RESEARCH] Permission to get API data from OpenAcc web | D32: Team Mobile | E32: CR | G32: Medium | I32: Q2 | K32: phongvo@phs.vn | M32: phongvo2440 | N32: phongvo2440
A33: 2216483 | C33: [CR] [2216483] [MSD] LOYALTY SYSTEM ON MOBILE APP | D33: Team Mobile | E33: CR | F33: MSD | G33: Medium | I33: Q2 | K33: phongvo@phs.vn | N33: phongvo2440 | O33: 2216483
A34: 2400512 | C34: [SDK] [2400512] Upgrade the iOS and Android SDKs in accordance with the requirements of Apple and Google | D34: Team Mobile | E34: SDK | G34: Medium | I34: Q2 | K34: phongvo@phs.vn | M34: phongvo2440 | N34: phongvo2440
A35: 2222464 | C35: [CR] [2222464] [RMD] Add sign-in method | D35: Team Mobile | E35: CR | F35: RMD | G35: Medium | I35: Q2 | K35: phongvo@phs.vn | M35: phongvo2440 | N35: phongvo2440 | O35: 2222464
A36: 2212813 | C36: [CR] [2212813] [SS] Derivatives Order Placement UI Enhancement | D36: Team Mobile | E36: CR | F36: SS | G36: Low | I36: Q2 | K36: phongvo@phs.vn | N36: phongvo2440
A37: 2174942 | C37: [CR] [2174942] [MSD] Automation Test Proposal | D37: Team Mobile | E37: CR | F37: MSD | G37: Medium | I37: Backlog | K37: phongvo@phs.vn | M37: phongvo2440 | N37: phongvo2440
A38: 2289280 | C38: [CR] [2289280] [FN] Future-Dated Withdrawal Scheduling for Customers | D38: Team Mobile | E38: CR | F38: FN | G38: Medium | I38: Backlog | K38: phongvo@phs.vn | N38: phongvo2440 | O38: 2289280
A39: 2317336 | C39: [CR] [2317336] [AC] Proposal to implement an automated cash dividend reinvestment service (Auto-DRIP) on PHS Elite app | D39: Team Mobile | E39: CR | F39: AC | G39: Low | I39: Backlog | K39: phongvo@phs.vn | N39: phongvo2440
A40: 2307583 | C40: [CR] [2307583] PHS BondTerm – Fixed-Tenor Bond Investment Package (via Listed Bonds | D40: Team Mobile | E40: CR | G40: Medium | I40: Backlog | K40: phongvo@phs.vn | M40: phongvo2440 | N40: phongvo2440
A41: 2330515 | C41: [CR] [2330515] IPO Share Subscription Feature | D41: Team Mobile | E41: CR | G41: Medium | I41: Backlog | K41: phongvo@phs.vn | M41: phongvo2440 | N41: phongvo2440 | O41: 2330515
A42: 2376660 | C42: [CR] [2376660] Assessment of Requirements from RAR Center for the VNeID Integration into the eKYC Account Opening Process Project | D42: Team Mobile | E42: CR | G42: Medium | I42: Backlog | K42: phongvo@phs.vn | M42: phongvo2440 | N42: phongvo2440
A43: 2397922 | C43: [CR] [2397922] Enhance filter for Elite Fund | D43: Team Mobile | E43: CR | G43: Medium | I43: Backlog | K43: phongvo@phs.vn | M43: phongvo2440 | N43: phongvo2440
A44: 2415056 | C44: [CR] [2415056] [MKT] Implementation of “Partner Offers” on PHS Mobile App | D44: Team Mobile | E44: CR | F44: MKT | G44: Medium | I44: Backlog | K44: phongvo@phs.vn | M44: phongvo2440 | N44: phongvo2440 | O44: 2415056
A45: 2291957 | C45: [CR] [2291957] [IC] Update the account opening function on the PHS Elite app login screen | D45: Team Mobile | E45: CR | F45: IC | G45: Medium | I45: Backlog | K45: phongvo@phs.vn | M45: phongvo2440 | N45: phongvo2440
A46: 2482578 | C46: [CR] [2482578] [AC] Upgrade the QR Code Deposit Function on the PHS App | D46: Team Mobile | E46: CR | F46: AC | G46: Medium | I46: Backlog | K46: phongvo@phs.vn | M46: phongvo2440 | N46: phongvo2440
C47: [CR] [2310394 - 2391899] [KT] [No.01-2026] Tax analysis and estimation tools for investors. | D47: MW Team | E47: CR | G47: Medium | I47: Q2 | K47: huunguyen@phs.vn | M47: huunguyen2525 | N47: huunguyen2525
A48: 2446191 | C48: [CR] [2446191] [MSD] [No.08-2026] VCF0051 – Adjust Report Extraction Conditions | D48: MW Team | E48: CR | F48: MSD | G48: Medium | I48: Q2 | K48: huunguyen@phs.vn | M48: huunguyen2525 | N48: huunguyen2525
A49: 2238356 | C49: [CR] [2238356] [MSD] [No.27-2025]ADVANCE MARGIN FOR DERIVATIVES | D49: MW Team | E49: CR | F49: MSD | G49: Medium | I49: Q2 | K49: huunguyen@phs.vn | M49: huunguyen2525 | N49: huunguyen2525 | O49: 2238356
A50: 2084592 | C50: [CR] [2084592] [RMD] [No.10-2025] Calculate interest for accounts using special interest rate products | D50: MW Team | E50: CR | F50: RMD | G50: Medium | I50: Q2 | K50: huunguyen@phs.vn | M50: huunguyen2525 | N50: huunguyen2525 | O50: 2084592
A51: 2222464 | C51: [CR] [2222464] [RMD] [No.09-2025] Add sign-in method | D51: MW Team | E51: CR | F51: RMD | G51: Medium | I51: Q2 | K51: huunguyen@phs.vn | M51: huunguyen2525 | N51: huunguyen2525 | O51: 2222464
A52: 2443571 | C52: [CR] [2443571] [SS] [No.09-2026] Restrict using PHS email address for securities transactions | D52: MW Team | E52: CR | F52: SS | G52: Medium | I52: Q2 | K52: huunguyen@phs.vn | M52: huunguyen2525 | N52: huunguyen2525
A53: 2149046 | C53: [CR] [2149046] [SS] [No.28-2025] Adjustment of the account opening flow on the PHS ELITE TRADING application | D53: MW Team | E53: CR | F53: SS | G53: Medium | I53: Q2 | K53: huunguyen@phs.vn | M53: huunguyen2525 | N53: huunguyen2525 | O53: 2149046
A54: 2133352 | C54: [CR] [2133352] [RMD] [No.12-2025] Margin product calculation tool | D54: MW Team | E54: CR | F54: RMD | G54: Medium | I54: Q2 | K54: huunguyen@phs.vn | M54: huunguyen2525 | N54: huunguyen2525 | O54: 2133352
A55: 2246969 | C55: [CR] [2246969] [DTD] [No.39-2025] Add PCA trading stock labels and implement stock filtering features on the PHS Elite app | D55: MW Team | E55: CR | F55: DTD | G55: Medium | I55: Q2 | K55: huunguyen@phs.vn | M55: huunguyen2525 | N55: huunguyen2525
A56: 2106995 | C56: [CR] [2106995] [DTD] [No.25-2025] Add put-through order trading feature on PHS ELITE XPRO | D56: MW Team | E56: CR | F56: DTD | G56: Medium | I56: Q2 | K56: huunguyen@phs.vn | M56: huunguyen2525 | N56: huunguyen2525
A57: 2275303 | C57: [CR] [2275303] [DTD] [No.1-2026] Enhance securities depository features via the PHS Elite Trading application | D57: MW Team | E57: CR | F57: DTD | G57: Medium | I57: Q2 | K57: huunguyen@phs.vn | M57: huunguyen2525 | N57: huunguyen2525 | O57: 2275303
A58: 2216483 | C58: [CR] [2216483] [MSD] [No.33-2025] Loyalty Customer System | D58: MW Team | E58: CR | F58: MSD | G58: Medium | I58: Q2 | K58: huunguyen@phs.vn | M58: huunguyen2525 | N58: huunguyen2525 | O58: 2216483
A59: 2437753 | C59: [CR] [2437753] [SS] [No.07-2026] AF & LN Duplication & Bulk Import Function | D59: MW Team | E59: CR | F59: SS | G59: Medium | I59: Q2 | K59: huunguyen@phs.vn | M59: huunguyen2525 | N59: huunguyen2525
A60: 2283752 | C60: [CR] [2283752] [DTD] [No.03-2026] Send Notification via Elite App and mail all right issue | D60: MW Team | E60: CR | F60: DTD | G60: Medium | I60: Q2 | K60: huunguyen@phs.vn | M60: huunguyen2525 | N60: huunguyen2525 | O60: 2283752
A61: 2289280 | C61: [CR] [2289280] [FN] [No.01-2026] Future-Dated Withdrawal Scheduling for Customers | D61: MW Team | E61: CR | F61: FN | G61: Medium | I61: Backlog | K61: huunguyen@phs.vn | M61: huunguyen2525 | N61: huunguyen2525 | O61: 2289280
A62: 2133352 | C62: [CR] [2133352] [RMD] Margin product calculation tool | D62: Team Mobile | E62: CR | F62: RMD | G62: Medium | I62: Q1 | K62: phongvo@phs.vn | M62: phongvo2440 | N62: phongvo2440 | O62: 2133352
A63: 2247969 | C63: [CR] [2247969] [SS] Add PCA trading stock labels and implement stock filtering features on the PHS Elite app | D63: Team Mobile | E63: CR | F63: SS | G63: Medium | I63: Q1 | K63: phongvo@phs.vn | M63: phongvo2440 | N63: phongvo2440
A64: 2186435 | C64: [CR] [2186435] [MSD] PROMOTION REGISTRATION FUNCTION UPGRADE | D64: Team Mobile | E64: CR | F64: MSD | G64: Medium | I64: Q1 | K64: phongvo@phs.vn | M64: phongvo2440 | N64: phongvo2440 | O64: 2186435
A65: 2285823 | C65: [CR] [2285823] [IC] THE LOGIN SCREEN GREETING MESSAGE | D65: Team Mobile | E65: CR | F65: IC | G65: Medium | I65: Q1 | K65: phongvo@phs.vn | M65: phongvo2440 | N65: phongvo2440
A66: 2224919 | C66: [CR] [2224919] [SS] Feature to save multiple login accounts on a single device in the PHS Elite Trading app | D66: Team Mobile | E66: CR | F66: SS | G66: Medium | I66: Q1 | K66: phongvo@phs.vn | M66: phongvo2440 | N66: phongvo2440
A67: 2302697 | C67: [CR] [2302697] [LG] Add content regarding personal data protection | D67: Team Mobile | E67: CR | F67: LG | G67: Low | I67: Q1 | K67: phongvo@phs.vn | N67: phongvo2440
A68: 2185585 | C68: [CR] [2185585] [IT] Add the Reward Redemption feature to the PHS Elite Trading application | D68: Team Mobile | E68: CR | F68: IT | G68: Medium | I68: Q1 | K68: phongvo@phs.vn | M68: phongvo2440 | N68: phongvo2440
A69: 2154685 | C69: [CR] [2154685] [INB] Mutual Fund Distribution (Phase 2) | D69: Team Mobile | E69: CR | F69: INB | G69: Medium | I69: Q1 | K69: phongvo@phs.vn | N69: phongvo2440 | O69: 2154685
C70: [MKT] Update Logo PHS 20 years anniversary | D70: Team Mobile | E70: Internal | G70: Medium | I70: Q1 | K70: phongvo@phs.vn | M70: phongvo2440 | N70: phongvo2440
A71: 2077975 | C71: [CR] [2077975] [MKT] Collaboration with Woori Bank Proposal | D71: Team Mobile | E71: CR | F71: MKT | G71: Low | I71: Q1 | K71: phongvo@phs.vn | N71: phongvo2440
A72: 2196774 | C72: [CR] [2196774] [INB] Proposed modifications of Mobile UI and middleware modules to facilitate Elite Seeds sub-account deployment | D72: Team Mobile | E72: CR | F72: INB | G72: Medium | I72: Q1 | K72: phongvo@phs.vn | M72: phongvo2440 | N72: phongvo2440
A73: 2242463 | C73: [CR] [2242463] [MSD] PROMOTION: HORSE YEAR FORTUNE 2026 | D73: Team Mobile | E73: CR | F73: MSD | G73: Medium | I73: Q1 | K73: phongvo@phs.vn | M73: phongvo2440 | N73: phongvo2440
A74: 2185583 | C74: [CR] [2185583] [IT] Enhancement of the Smart OTP Function on the PHS Elite Trading Application | D74: Team Mobile | E74: CR | F74: IT | G74: Medium | I74: Q1 | K74: phongvo@phs.vn | M74: phongvo2440 | N74: phongvo2440
A75: 2213580 | C75: [CR] [2213580] [CCC] Enhancement Successful Reward Redemption Notifications via Email and the PHS Elite Trading App | D75: Dev Team B | E75: CR | F75: CCC | G75: Medium | I75: Q1 | K75: minhvo@phs.vn | M75: minhvo2565 | N75: minhvo2565
A76: 2186435 | C76: [CR] [2186435] [MSD] Enhance Promotion features on Admin Customer Portal | D76: Dev Team B | E76: CR | F76: MSD | G76: Medium | I76: Q1 | K76: minhvo@phs.vn | M76: minhvo2565 | N76: minhvo2565 | O76: 2186435
A77: 2065876 | C77: [CR] [2065876] [MSD] Add a feature to view the registration/deletion history of beneficiary accounts (Same-owner transfer) on the Admin Customer Portal | D77: Dev Team B | E77: CR | F77: MSD | G77: Medium | I77: Q1 | K77: minhvo@phs.vn | M77: minhvo2565 | N77: minhvo2565
A78: 1722552 | C78: [CR] [1722552] [BMD] Provide API data source for Transaction fluctuation function in Broker portal | D78: Dev Team B | E78: CR | F78: BMD | G78: Medium | I78: Q1 | K78: minhvo@phs.vn | M78: minhvo2565 | N78: minhvo2565

Sheet Team Config
A1: Team Name | B1: Team Lead | C1: Lead Email | D1: Members Count
A2: Team Mobile | B2: Phong Vo | C2: phongvo@phs.vn
A3: Dev Team B | B3: Minh Vo | C3: minhvo@phs.vn
A4: MW Team | B4: Huu Nguyen | C4: huunguyen@phs.vn

Sheet Naming Convention
A1: Task Naming Convention Guide
A2: Pattern | B2: Example | C2: Description | D2: Field Mapping
A3: [CR] [request-id] [dept] Title | B3: [CR] [2329940] [RS] AI Chatbot Integration | C3: Standard CR task — request-id is the ID from the base request platform | D3: Request ID → column A
A4: [CR] [request-id] [dept] [No.XX-YYYY] Title | B4: [CR] [2084592] [RMD] [No.10-2025] Calculate interest | C4: MW Team format with internal sequence number and year | D4: No.XX-YYYY tracks internal ordering
A5: [SDK] [request-id] Title | B5: [SDK] [2400512] Upgrade iOS and Android SDKs | C5: SDK upgrade tasks | D5: Category = SDK
A6: [dept] Title (no CR) | B6: [MKT] Update Logo PHS 20 years anniversary | C6: Internal task without CR number | D6: Category = Internal
A8: Mandatory Fields & Rules
A9: 1. Every task MUST have: Request ID, Task Name, Team, Status, Assignee, Team Lead, Created Date, Deadline.
A10: 2. Backlog tasks: Status = "Todo", Phase = "Backlog". Must be groomed with deadline before moving to "Doing".
A11: 3. Request ID is the unique identifier from the base request platform — use it to detect duplicates across teams.
A12: 4. If the same CR spans multiple teams, create ONE row per team with the SAME Request ID. Use Dependencies column to link them.
A13: 5. Status flow: Todo → Doing → Done | Todo → Doing → Overdue → Done | Any → Blocked (explain in Notes).
A14: 6. Multi-team CRs: When a CR spans multiple teams, append the team scope to the task name: [CR] [request-id] [dept] Title — Scope (e.g., "— Mobile UI", "— Middleware API", "— Web Admin"). Use the SAME Request ID across all rows.
A15: 7. CR Overview sheet: For every multi-team CR, maintain ONE row in the CR Overview sheet summarizing all teams’ statuses. Update the Overall Status whenever any team’s status changes.

Sheet Dashboard Summary
A1: Auto-calculated Dashboard (COUNTIFS from Task Tracker)
A3: Team | B3: Total | C3: Todo | D3: Doing | E3: Done | F3: Overdue | G3: Blocked
A4: Team Mobile | B4: =COUNTIF('Task Tracker'!D:D,"Team Mobile") | C4: =COUNTIFS('Task Tracker'!D:D,"Team Mobile",'Task Tracker'!H:H,"Todo") | D4: =COUNTIFS('Task Tracker'!D:D,"Team Mobile",'Task Tracker'!H:H,"Doing") | E4: =COUNTIFS('Task Tracker'!D:D,"Team Mobile",'Task Tracker'!H:H,"Done") | F4: =COUNTIFS('Task Tracker'!D:D,"Team Mobile",'Task Tracker'!H:H,"Overdue") | G4: =COUNTIFS('Task Tracker'!D:D,"Team Mobile",'Task Tracker'!H:H,"Blocked")
A5: Dev Team B | B5: =COUNTIF('Task Tracker'!D:D,"Dev Team B") | C5: =COUNTIFS('Task Tracker'!D:D,"Dev Team B",'Task Tracker'!H:H,"Todo") | D5: =COUNTIFS('Task Tracker'!D:D,"Dev Team B",'Task Tracker'!H:H,"Doing") | E5: =COUNTIFS('Task Tracker'!D:D,"Dev Team B",'Task Tracker'!H:H,"Done") | F5: =COUNTIFS('Task Tracker'!D:D,"Dev Team B",'Task Tracker'!H:H,"Overdue") | G5: =COUNTIFS('Task Tracker'!D:D,"Dev Team B",'Task Tracker'!H:H,"Blocked")
A6: MW Team | B6: =COUNTIF('Task Tracker'!D:D,"MW Team") | C6: =COUNTIFS('Task Tracker'!D:D,"MW Team",'Task Tracker'!H:H,"Todo") | D6: =COUNTIFS('Task Tracker'!D:D,"MW Team",'Task Tracker'!H:H,"Doing") | E6: =COUNTIFS('Task Tracker'!D:D,"MW Team",'Task Tracker'!H:H,"Done") | F6: =COUNTIFS('Task Tracker'!D:D,"MW Team",'Task Tracker'!H:H,"Overdue") | G6: =COUNTIFS('Task Tracker'!D:D,"MW Team",'Task Tracker'!H:H,"Blocked")
A7: TOTAL | B7: =SUM(B4:B6) | C7: =SUM(C4:C6) | D7: =SUM(D4:D6) | E7: =SUM(E4:E6) | F7: =SUM(F4:F6) | G7: =SUM(G4:G6)
A9: Breakdown by Phase
A10: Team | B10: Q1 | C10: Q2 | D10: Q3 | E10: Q4 | F10: Backlog | G10: Total
A11: Team Mobile | B11: =COUNTIFS('Task Tracker'!D:D,"Team Mobile",'Task Tracker'!I:I,"Q1") | C11: =COUNTIFS('Task Tracker'!D:D,"Team Mobile",'Task Tracker'!I:I,"Q2") | D11: =COUNTIFS('Task Tracker'!D:D,"Team Mobile",'Task Tracker'!I:I,"Q3") | E11: =COUNTIFS('Task Tracker'!D:D,"Team Mobile",'Task Tracker'!I:I,"Q4") | F11: =COUNTIFS('Task Tracker'!D:D,"Team Mobile",'Task Tracker'!I:I,"Backlog") | G11: =SUM(B11:F11)
A12: Dev Team B | B12: =COUNTIFS('Task Tracker'!D:D,"Dev Team B",'Task Tracker'!I:I,"Q1") | C12: =COUNTIFS('Task Tracker'!D:D,"Dev Team B",'Task Tracker'!I:I,"Q2") | D12: =COUNTIFS('Task Tracker'!D:D,"Dev Team B",'Task Tracker'!I:I,"Q3") | E12: =COUNTIFS('Task Tracker'!D:D,"Dev Team B",'Task Tracker'!I:I,"Q4") | F12: =COUNTIFS('Task Tracker'!D:D,"Dev Team B",'Task Tracker'!I:I,"Backlog") | G12: =SUM(B12:F12)
A13: MW Team | B13: =COUNTIFS('Task Tracker'!D:D,"MW Team",'Task Tracker'!I:I,"Q1") | C13: =COUNTIFS('Task Tracker'!D:D,"MW Team",'Task Tracker'!I:I,"Q2") | D13: =COUNTIFS('Task Tracker'!D:D,"MW Team",'Task Tracker'!I:I,"Q3") | E13: =COUNTIFS('Task Tracker'!D:D,"MW Team",'Task Tracker'!I:I,"Q4") | F13: =COUNTIFS('Task Tracker'!D:D,"MW Team",'Task Tracker'!I:I,"Backlog") | G13: =SUM(B13:F13)

Sheet CR Overview
A1: CR Overview — Cross-Team Change Request Tracking
A2: Each row = one unique CR. Shows which teams are involved, per-team status, and overall CR health. Manually maintained — reference Task Tracker for source data.
A3: Request ID | B3: CR Title | C3: Dept | D3: Priority | E3: Teams Involved | F3: Mobile Status | G3: Dev B Status | H3: MW Status | I3: Overall Status | J3: Blockers / Notes
A4: 2084592 | B4: Calculate interest for accounts using special interest rate products | C4: RMD | D4: Medium | E4: 3 teams | I4: In Progress
A5: 2275303 | B5: Enhance securities depository features via the PHS Elite Trading application | C5: SS | D5: Medium | E5: 3 teams | I5: In Progress
A6: 2133352 | B6: Margin product calculation tool | C6: RMD | D6: Medium | E6: 2 teams | G6: — | I6: In Progress
A7: 2149046 | B7: EKYC | C7: IT | D7: Medium | E7: 2 teams | G7: — | I7: In Progress
A8: 2154685 | B8: Upgrade fund certificate trading feature on Mobile app | C8: BMD | D8: Medium | E8: 2 teams | H8: — | I8: In Progress
A9: 2186435 | B9: PROMOTION REGISTRATION FUNCTION UPGRADE | C9: MSD | D9: Medium | E9: 2 teams | H9: — | I9: In Progress
A10: 2216483 | B10: LOYALTY SYSTEM ON MOBILE APP | C10: MSD | D10: Medium | E10: 2 teams | G10: — | I10: In Progress
A11: 2222464 | B11: Add sign-in method | C11: RMD | D11: Medium | E11: 2 teams | G11: — | I11: In Progress
A12: 2238356 | B12: ADVANCE MARGIN FOR DERIVATIVES | C12: MSD | D12: Medium | E12: 2 teams | G12: — | I12: In Progress
A13: 2283752 | B13: Send Notification via Elite App and mail all right issue | C13: SS | D13: Medium | E13: 2 teams | G13: — | I13: In Progress
A14: 2289280 | B14: Future-Dated Withdrawal Scheduling for Customers | C14: FN | D14: Medium | E14: 2 teams | G14: — | I14: In Progress
A15: 2330515 | B15: IPO Share Subscription Feature | C15: RMD | D15: Medium | E15: 2 teams | H15: — | I15: In Progress
A16: 2335404 | B16: Upgrade the automatic limit adjustment feature | D16: Medium | E16: 2 teams | H16: — | I16: In Progress
A17: 2400155 | B17: Develop Mission Tracking Page for Promotion | C17: MKT | D17: Medium | E17: 2 teams | H17: — | I17: In Progress
A18: 2415056 | B18: Implementation of “Partner Offers” on PHS Mobile App | C18: MKT | D18: Medium | E18: 2 teams | H18: — | I18: In Progress
A19: 1722552 | B19: Provide API data source for Transaction fluctuation function in Broker portal | C19: BMD | D19: Medium | E19: 1 team | F19: — | H19: — | I19: In Progress
A20: 1923581 | B20: Tool to control the number of positions that need to be closed out | C20: RMD | D20: Medium | E20: 1 team | F20: — | H20: — | I20: In Progress
A21: 1954732 | B21: HR report automation | C21: HR | D21: Medium | E21: 1 team | F21: — | H21: — | I21: In Progress
A22: 2065876 | B22: Add a feature to view the registration/deletion history of beneficiary accounts (Same-owner transfer) on the Admin Customer Portal | C22: MSD | D22: Medium | E22: 1 team | F22: — | H22: — | I22: In Progress
A23: 2106995 | B23: Add put-through order trading feature on PHS ELITE XPRO | C23: DTD | D23: Medium | E23: 1 team | F23: — | G23: — | I23: In Progress
A24: 2129248 | B24: Add Special room information for Locations | C24: RMD | D24: Medium | E24: 1 team | F24: — | H24: — | I24: In Progress
A25: 2174942 | B25: Automation Test Proposal | C25: MSD | D25: Medium | E25: 1 team | G25: — | H25: — | I25: In Progress
A26: 2185583 | B26: Enhancement of the Smart OTP Function on the PHS Elite Trading Application | C26: IT | D26: Medium | E26: 1 team | G26: — | H26: — | I26: In Progress
A27: 2185585 | B27: Add the Reward Redemption feature to the PHS Elite Trading application | C27: IT | D27: Medium | E27: 1 team | G27: — | H27: — | I27: In Progress
A28: 2196774 | B28: Proposed modifications of Mobile UI and middleware modules to facilitate Elite Seeds sub-account deployment | C28: INB | D28: Medium | E28: 1 team | G28: — | H28: — | I28: In Progress
A29: 2197982 | B29: Research Landing Page: All Features & Phase 1 Execution | C29: RS | D29: Medium | E29: 1 team | F29: — | H29: — | I29: In Progress
A30: 2213580 | B30: Enhancement Successful Reward Redemption Notifications via Email and the PHS Elite Trading App | C30: CCC | D30: Medium | E30: 1 team | F30: — | H30: — | I30: In Progress
A31: 2224919 | B31: Feature to save multiple login accounts on a single device in the PHS Elite Trading app | C31: SS | D31: Medium | E31: 1 team | G31: — | H31: — | I31: In Progress
A32: 2242463 | B32: PROMOTION: HORSE YEAR FORTUNE 2026 | C32: MSD | D32: Medium | E32: 1 team | G32: — | H32: — | I32: In Progress
A33: 2246969 | B33: Add PCA trading stock labels and implement stock filtering features on the PHS Elite app | C33: DTD | D33: Medium | E33: 1 team | F33: — | G33: — | I33: In Progress
A34: 2247969 | B34: Add PCA trading stock labels and implement stock filtering features on the PHS Elite app | C34: SS | D34: Medium | E34: 1 team | G34: — | H34: — | I34: In Progress
A35: 2285823 | B35: THE LOGIN SCREEN GREETING MESSAGE | C35: IC | D35: Medium | E35: 1 team | G35: — | H35: — | I35: In Progress
A36: 2291957 | B36: Update the account opening function on the PHS Elite app login screen | C36: IC | D36: Medium | E36: 1 team | G36: — | H36: — | I36: In Progress
A37: 2306127 | B37: INB_ Proposal to implement the mobile app notifications for Elite Seeds | D37: Medium | E37: 1 team | G37: — | H37: — | I37: In Progress
A38: 2307583 | B38: PHS BondTerm – Fixed-Tenor Bond Investment Package (via Listed Bonds | D38: Medium | E38: 1 team | G38: — | H38: — | I38: In Progress
A39: 2310394 | B39: Tax analysis and estimation tools for investors (Phase 1) | D39: Medium | E39: 1 team | G39: — | H39: — | I39: In Progress
A40: 2372910 | B40: [RESEARCH] Permission to get API data from OpenAcc web | D40: Medium | E40: 1 team | G40: — | H40: — | I40: In Progress
A41: 2376660 | B41: Assessment of Requirements from RAR Center for the VNeID Integration into the eKYC Account Opening Process Project | D41: Medium | E41: 1 team | G41: — | H41: — | I41: In Progress
A42: 2385402 | B42: Create popup on web phs.vn to promote for landing page PHS 20 Years Anniversary | C42: MKT | D42: Medium | E42: 1 team | F42: — | H42: — | I42: In Progress
A43: 2397922 | B43: Enhance filter for Elite Fund | D43: Medium | E43: 1 team | G43: — | H43: — | I43: In Progress
A44: 2400512 | B44: Upgrade the iOS and Android SDKs in accordance with the requirements of Apple and Google | D44: Medium | E44: 1 team | G44: — | H44: — | I44: In Progress
A45: 2403987 | B45: Loyalty System - Phase 1 | C45: SS | D45: Medium | E45: 1 team | F45: — | H45: — | I45: In Progress
A46: 2423945 | B46: Enhance the promotional declaration feature on the Admin Portal | C46: SS | D46: Medium | E46: 1 team | F46: — | H46: — | I46: In Progress
A47: 2425861 | B47: Research Portal: Phase 2 | C47: RS | D47: Medium | E47: 1 team | F47: — | H47: — | I47: In Progress
A48: 2426812 | B48: Merge CCC & RS chatbot into one Master Client Chatbot | C48: MKT | D48: Medium | E48: 1 team | F48: — | H48: — | I48: In Progress
A49: 2437753 | B49: AF & LN Duplication & Bulk Import Function | C49: SS | D49: Medium | E49: 1 team | F49: — | G49: — | I49: In Progress
A50: 2443571 | B50: Restrict using PHS email address for securities transactions | C50: SS | D50: Medium | E50: 1 team | F50: — | G50: — | I50: In Progress
A51: 2446191 | B51: VCF0051 – Adjust Report Extraction Conditions | C51: MSD | D51: Medium | E51: 1 team | F51: — | G51: — | I51: In Progress
A52: 2482578 | B52: Upgrade the QR Code Deposit Function on the PHS App | C52: AC | D52: Medium | E52: 1 team | G52: — | H52: — | I52: In Progress
A53: 2077975 | B53: Collaboration with Woori Bank Proposal | C53: MKT | D53: Low | E53: 1 team | G53: — | H53: — | I53: In Progress
A54: 2212813 | B54: Derivatives Order Placement UI Enhancement | C54: SS | D54: Low | E54: 1 team | G54: — | H54: — | I54: In Progress
A55: 2302697 | B55: Add content regarding personal data protection | C55: LG | D55: Low | E55: 1 team | G55: — | H55: — | I55: In Progress
A56: 2317336 | B56: Proposal to implement an automated cash dividend reinvestment service (Auto-DRIP) on PHS Elite app | C56: AC | D56: Low | E56: 1 team | G56: — | H56: — | I56: In Progress
A57: 2329940 | B57: AI Chatbot Integration for Elite Mobile App & Xpro Web Trading | C57: RS | D57: Low | E57: 1 team | G57: — | H57: — | I57: In Progress
A59: Summary
A60: Total unique CRs: | B60: =COUNTA(A4:A57)
A61: Multi-team CRs: | B61: =COUNTIF(E4:E57,"2 teams")+COUNTIF(E4:E57,"3 teams")
A62: CRs with Overdue status: | B62: =COUNTIF(I4:I57,"Overdue")
A63: CRs fully Done: | B63: =COUNTIF(I4:I57,"Done")
A64: CRs Partially Done: | B64: =COUNTIF(I4:I57,"Partially Done")
A65: CRs In Progress: | B65: =COUNTIF(I4:I57,"In Progress")
A66: CRs Blocked: | B66: =COUNTIF(I4:I57,"Blocked")
